ecotag_sdk/__init__.py
ecotag_sdk/ecotag.py
ecotag_sdk-0.1.2.dist-info/METADATA
ecotag_sdk-0.1.2.dist-info/WHEEL
ecotag_sdk-0.1.2.dist-info/RECORD
